model_reviews/__init__.py
model_reviews/apps.py
model_reviews/constants.py
model_reviews/emails.py
model_reviews/forms.py
model_reviews/formset.py
model_reviews/models.py
model_reviews/settings.py
model_reviews/side_effects.py
model_reviews/signals.py
model_reviews/urls.py
model_reviews/utils.py
model_reviews/views.py
model_reviews/migrations/0001_initial.py
model_reviews/migrations/0002_auto_20200918_2141.py
model_reviews/migrations/__init__.py
model_reviews/templates/comments/form.html
model_reviews/templates/comments/list.html
model_reviews/templates/model_reviews/bulk.html
model_reviews/templates/model_reviews/modelreview_detail.html
model_reviews/templates/model_reviews/email/generic_email_body.html
model_reviews/templates/model_reviews/email/generic_email_body.txt
model_reviews/templates/model_reviews/email/generic_email_subject.txt
django_model_reviews-1.4.0.dist-info/LICENSE
django_model_reviews-1.4.0.dist-info/METADATA
django_model_reviews-1.4.0.dist-info/WHEEL
django_model_reviews-1.4.0.dist-info/top_level.txt
django_model_reviews-1.4.0.dist-info/RECORD
