Metadata-Version: 2.1
Name: django-model-reviews
Version: 1.4.0
Summary: Easy moderation of changes made to Django models
Home-page: https://github.com/moshthepitt/django-model-reviews
Author: Kelvin Jayanoris
Author-email: kelvin@jayanoris.com
License: MIT
Platform: UNKNOWN
Classifier: Programming Language :: Python
Classifier: Programming Language :: Python :: 3.6
Classifier: Programming Language :: Python :: 3.7
Classifier: Programming Language :: Python :: 3.8
Classifier: Framework :: Django
Classifier: Framework :: Django :: 2.2
Classifier: Framework :: Django :: 3.0
Requires-Dist: Django (>=2.2)
Requires-Dist: django-braces
Requires-Dist: django-contrib-comments
